README.md
setup.py
flextape/__init__.py
flextape/flextape.py
flextape.py.egg-info/PKG-INFO
flextape.py.egg-info/SOURCES.txt
flextape.py.egg-info/dependency_links.txt
flextape.py.egg-info/top_level.txt