Metadata-Version: 1.0
Name: flextape.py
Version: 0.0.2
Summary: Flextape but it's python.
Home-page: https://gitlab.com/sparskakyl/flextape-py
Author: sparskakyl
Author-email: lykakspars@cock.li
License: MIT
Keywords: flextape,jontron,phil,meme
Platform: UNKNOWN
